rpi_automator/EventDispatcher.py
rpi_automator/__init__.py
rpi_automator/datastores/DataStore.py
rpi_automator/datastores/DynamoDBDataStore.py
rpi_automator/datastores/__init__.py
rpi_automator/dto/HumidityPIDData.py
rpi_automator/dto/LocalFileData.py
rpi_automator/dto/ModuleResult.py
rpi_automator/dto/RelaySwitchData.py
rpi_automator/dto/TempAndHumidityData.py
rpi_automator/dto/UploadedFileData.py
rpi_automator/dto/__init__.py
rpi_automator/modules/BaseModule.py
rpi_automator/modules/ButtonDetector.py
rpi_automator/modules/CV2Camera.py
rpi_automator/modules/DoNothing.py
rpi_automator/modules/PICamera.py
rpi_automator/modules/RelaySwitch.py
rpi_automator/modules/S3Uploader.py
rpi_automator/modules/TempHumiditySensor.py
rpi_automator/modules/VeSyncOutlet.py
rpi_automator/modules/__init__.py
rpi_automator/tests/EventControllerTests.py
rpi_automator/tests/__init__.py
rpi_automator/tests/integration.py
rpi_automator/tests/module_mocks.py
rpi_automator/util/ModuleUtils.py
rpi_automator/util/PID.py
rpi_automator/util/__init__.py
rpi_automator-0.0.4.data/scripts/rpi_automator
rpi_automator-0.0.4.dist-info/LICENSE
rpi_automator-0.0.4.dist-info/METADATA
rpi_automator-0.0.4.dist-info/WHEEL
rpi_automator-0.0.4.dist-info/top_level.txt
rpi_automator-0.0.4.dist-info/RECORD
